{
    "id": "base1-20",
    "name": "Electabuzz",
    "number": "20",
    "setId": "base1",
    "rarity": "Rare",
    "priceChartingIds": {
        "normal": "630433",
        "1st-edition": "715609",
        "shadowless": "715711"
    },
    "priceHistory": {
        "2024-06-27": {
            "normal": {
                "ungraded": "$4.25",
                "psa10": "$69.99",
                "grade9": "$21.65"
            },
            "1st-edition": {
                "ungraded": "$62.93",
                "psa10": "$747.50",
                "grade9": "$150.00"
            },
            "shadowless": {
                "ungraded": "$9.34",
                "psa10": "$127.50",
                "grade9": "$50.00"
            }
        }
    }
}