{
    "id": "pl2-54",
    "name": "Whiscash E4",
    "number": "54",
    "setId": "pl2",
    "rarity": "Uncommon",
    "priceChartingIds": {
        "normal": "925450",
        "reverse-holo": "925569"
    },
    "priceHistory": {
        "2024-06-27": {
            "normal": {
                "ungraded": "$1.10",
                "psa10": "",
                "grade9": ""
            },
            "reverse-holo": {
                "ungraded": "$1.95",
                "psa10": "",
                "grade9": ""
            }
        }
    }
}