{
    "id": "sm7-138",
    "name": "Lure Ball",
    "number": "138",
    "setId": "sm7",
    "rarity": "Uncommon",
    "priceChartingIds": {
        "normal": "962051",
        "reverse-holo": "962219"
    },
    "priceHistory": {
        "2024-06-27": {
            "normal": {
                "ungraded": "$0.99",
                "psa10": "",
                "grade9": ""
            },
            "reverse-holo": {
                "ungraded": "$2.00",
                "psa10": "",
                "grade9": ""
            }
        }
    }
}