{
    "id": "dp6-122",
    "name": "Staryu",
    "number": "122",
    "setId": "dp6",
    "rarity": "Common",
    "priceChartingIds": {
        "normal": "925053",
        "reverse-holo": "925196"
    },
    "priceHistory": {
        "2024-06-27": {
            "normal": {
                "ungraded": "$1.55",
                "psa10": "",
                "grade9": ""
            },
            "reverse-holo": {
                "ungraded": "$2.00",
                "psa10": "",
                "grade9": ""
            }
        }
    }
}