{
    "id": "swsh11-42",
    "name": "Snover",
    "number": "42",
    "setId": "swsh11",
    "rarity": "Common",
    "priceChartingIds": {
        "normal": "4049959",
        "reverse-holo": "4050175"
    },
    "priceHistory": {
        "2024-06-27": {
            "normal": {
                "ungraded": "$1.31",
                "psa10": "",
                "grade9": ""
            },
            "reverse-holo": {
                "ungraded": "$0.99",
                "psa10": "",
                "grade9": ""
            }
        }
    }
}