{
    "id": "xy9-79",
    "name": "Ferroseed",
    "number": "79",
    "setId": "xy9",
    "rarity": "Common",
    "priceChartingIds": {
        "normal": "959570",
        "reverse-holo": "959681"
    },
    "priceHistory": {
        "2024-06-27": {
            "normal": {
                "ungraded": "$0.88",
                "psa10": "$10.25",
                "grade9": ""
            },
            "reverse-holo": {
                "ungraded": "$1.06",
                "psa10": "",
                "grade9": ""
            }
        }
    }
}