{
    "id": "sv2-146",
    "name": "Grafaiai",
    "number": "146",
    "setId": "sv2",
    "rarity": "Uncommon",
    "priceChartingIds": {
        "normal": "5287435",
        "reverse-holo": "5287700"
    },
    "priceHistory": {
        "2024-06-27": {
            "normal": {
                "ungraded": "$1.41",
                "psa10": "$36.29",
                "grade9": "$12.02"
            },
            "reverse-holo": {
                "ungraded": "$1.25",
                "psa10": "$35.57",
                "grade9": "$11.79"
            }
        }
    }
}