{
    "id": "swsh8-146",
    "name": "Lucario V",
    "number": "146",
    "setId": "swsh8",
    "rarity": "Rare Holo V",
    "priceChartingIds": {
        "normal": "2771175",
        "jumbo": "4829801"
    },
    "priceHistory": {
        "2024-06-27": {
            "normal": {
                "ungraded": "$1.93",
                "psa10": "$32.99",
                "grade9": "$11.92"
            },
            "jumbo": {
                "ungraded": "$2.99",
                "psa10": "",
                "grade9": ""
            }
        }
    }
}