{
    "id": "swsh8-93",
    "name": "Luxray",
    "number": "93",
    "setId": "swsh8",
    "rarity": "Rare",
    "priceChartingIds": {
        "normal": "2771122",
        "reverse-holo": "2771387"
    },
    "priceHistory": {
        "2024-06-27": {
            "normal": {
                "ungraded": "$1.05",
                "psa10": "",
                "grade9": "$6.50"
            },
            "reverse-holo": {
                "ungraded": "$1.51",
                "psa10": "$35.95",
                "grade9": "$12.57"
            }
        }
    }
}