{
    "id": "xy1-131",
    "name": "Rainbow Energy",
    "number": "131",
    "setId": "xy1",
    "rarity": "Uncommon",
    "priceChartingIds": {
        "normal": "806624",
        "reverse-holo": "806748"
    },
    "priceHistory": {
        "2024-06-27": {
            "normal": {
                "ungraded": "$1.32",
                "psa10": "",
                "grade9": ""
            },
            "reverse-holo": {
                "ungraded": "$3.27",
                "psa10": "",
                "grade9": ""
            }
        }
    }
}