{
    "id": "swsh45-34",
    "name": "Rotom",
    "number": "34",
    "setId": "swsh45",
    "rarity": "Uncommon",
    "priceChartingIds": {
        "normal": "1341511",
        "reverse-holo": "1341701"
    },
    "priceHistory": {
        "2024-06-27": {
            "normal": {
                "ungraded": "$0.06",
                "psa10": "$31.80",
                "grade9": "$10.11"
            },
            "reverse-holo": {
                "ungraded": "$1.00",
                "psa10": "$13.83",
                "grade9": "$8.56"
            }
        }
    }
}