{
    "id": "swsh3-43",
    "name": "Galarian Darumaka",
    "number": "43",
    "setId": "swsh3",
    "rarity": "Common",
    "priceChartingIds": {
        "normal": "887129",
        "reverse-holo": "887313"
    },
    "priceHistory": {
        "2024-06-27": {
            "normal": {
                "ungraded": "$0.52",
                "psa10": "",
                "grade9": ""
            },
            "reverse-holo": {
                "ungraded": "$1.49",
                "psa10": "",
                "grade9": ""
            }
        }
    }
}