{
    "id": "bw5-35",
    "name": "Ducklett",
    "number": "35",
    "setId": "bw5",
    "rarity": "Common",
    "priceChartingIds": {
        "normal": "956081",
        "reverse-holo": "956191"
    },
    "priceHistory": {
        "2024-06-27": {
            "normal": {
                "ungraded": "$1.30",
                "psa10": "",
                "grade9": ""
            },
            "reverse-holo": {
                "ungraded": "$1.95",
                "psa10": "",
                "grade9": ""
            }
        }
    }
}