{
    "id": "sm6-16",
    "name": "Braixen",
    "number": "16",
    "setId": "sm6",
    "rarity": "Uncommon",
    "priceChartingIds": {
        "normal": "961679",
        "reverse-holo": "961825"
    },
    "priceHistory": {
        "2024-06-27": {
            "normal": {
                "ungraded": "$1.25",
                "psa10": "",
                "grade9": ""
            },
            "reverse-holo": {
                "ungraded": "$1.67",
                "psa10": "",
                "grade9": ""
            }
        }
    }
}