{
    "id": "hgss1-15",
    "name": "Ariados",
    "number": "15",
    "setId": "hgss1",
    "rarity": "Rare",
    "priceChartingIds": {
        "normal": "806128",
        "reverse-holo": "806233"
    },
    "priceHistory": {
        "2024-06-27": {
            "normal": {
                "ungraded": "$2.54",
                "psa10": "",
                "grade9": ""
            },
            "reverse-holo": {
                "ungraded": "$2.22",
                "psa10": "",
                "grade9": ""
            }
        }
    }
}