{
    "id": "sm9-74",
    "name": "Hitmonchan",
    "number": "74",
    "setId": "sm9",
    "rarity": "Uncommon",
    "priceChartingIds": {
        "normal": "962872",
        "reverse-holo": "963061"
    },
    "priceHistory": {
        "2024-06-27": {
            "normal": {
                "ungraded": "$1.26",
                "psa10": "$27.23",
                "grade9": "$12.88"
            },
            "reverse-holo": {
                "ungraded": "$2.55",
                "psa10": "$40.07",
                "grade9": "$15.84"
            }
        }
    }
}