{
    "id": "xy4-104",
    "name": "Shauna",
    "number": "104",
    "setId": "xy4",
    "rarity": "Uncommon",
    "priceChartingIds": {
        "normal": "958297",
        "reverse-holo": "958411"
    },
    "priceHistory": {
        "2024-06-27": {
            "normal": {
                "ungraded": "$1.23",
                "psa10": "",
                "grade9": ""
            },
            "reverse-holo": {
                "ungraded": "$1.25",
                "psa10": "",
                "grade9": "$2.00"
            }
        }
    }
}