{
    "id": "dp5-14",
    "name": "Zapdos",
    "number": "14",
    "setId": "dp5",
    "rarity": "Rare Holo",
    "priceChartingIds": {
        "normal": "921376",
        "reverse-holo": "921476"
    },
    "priceHistory": {
        "2024-06-27": {
            "normal": {
                "ungraded": "$12.66",
                "psa10": "$237.35",
                "grade9": "$95.42"
            },
            "reverse-holo": {
                "ungraded": "$9.69",
                "psa10": "$173.31",
                "grade9": "$84.35"
            }
        }
    }
}