{
    "id": "g1-72",
    "name": "Shauna",
    "number": "72",
    "setId": "g1",
    "rarity": "Uncommon",
    "priceChartingIds": {
        "normal": "959784",
        "reverse-holo": "2978709"
    },
    "priceHistory": {
        "2024-06-27": {
            "normal": {
                "ungraded": "$1.25",
                "psa10": "",
                "grade9": ""
            },
            "reverse-holo": {
                "ungraded": "$1.39",
                "psa10": "$56.59",
                "grade9": "$14.28"
            }
        }
    }
}